[
  {
    "@context": "http://www.w3.org/ns/anno.jsonld",
    "type": "Annotation",
    "body": [
      {
        "type": "TextualBody",
        "purpose": "describing",
        "format": "application/json",
        "value": {
          "script": "greek-1",
          "components": {
            "bottom-bar": {
              "features": [
                "straight",
                "sans-serif",
                "horizontal",
                "touching"
              ]
            },
            "downstroke": {
              "features": [
                "sans-serif",
                "straight",
                "vertical"
              ]
            },
            "middle-bar": {
              "features": [
                "sans-serif",
                "straight",
                "touching",
                "horizontal"
              ]
            },
            "top-bar": {
              "features": [
                "sans-serif",
                "touching",
                "horizontal",
                "straight"
              ]
            }
          },
          "tags": null,
          "textTarget": null,
          "character": "Ε"
        }
      }
    ],
    "target": [
      {
        "source": "https://apheleia.classics.ox.ac.uk/iipsrv/iipsrv.fcgi?IIIF=/inscription_images/ISic001420/ISic001420_copy4_tiled.tif",
        "selector": {
          "type": "FragmentSelector",
          "conformsTo": "http://www.w3.org/TR/media-frags/",
          "value": "xywh=pixel:1617.0107421875,1497.4793701171875,193.16064453125,237.7362060546875"
        }
      }
    ],
    "id": "https://crossreads.web.ox.ac.uk/annotations/5f39a22c-8f5d-4115-8ac4-0d175a6d75c7",
    "generator": "https://github.com/kingsdigitallab/crossreads#2023-09-01-00",
    "creator": "https://api.github.com/users/simonastoyanova",
    "created": "2024-02-22T14:38:57.385Z",
    "modifiedBy": "https://api.github.com/users/simonastoyanova",
    "modified": "2024-02-22T14:39:47.281Z"
  },
  {
    "@context": "http://www.w3.org/ns/anno.jsonld",
    "type": "Annotation",
    "body": [
      {
        "type": "TextualBody",
        "purpose": "describing",
        "format": "application/json",
        "value": {
          "script": "greek-1",
          "components": {
            "apex": {
              "features": [
                "angular"
              ]
            },
            "left-stroke": {
              "features": [
                "sans-serif",
                "straight",
                "diagonal"
              ]
            },
            "right-stroke": {
              "features": [
                "sans-serif",
                "straight",
                "diagonal"
              ]
            }
          },
          "tags": null,
          "textTarget": null,
          "character": "Υ"
        }
      }
    ],
    "target": [
      {
        "source": "https://apheleia.classics.ox.ac.uk/iipsrv/iipsrv.fcgi?IIIF=/inscription_images/ISic001420/ISic001420_copy4_tiled.tif",
        "selector": {
          "type": "FragmentSelector",
          "conformsTo": "http://www.w3.org/TR/media-frags/",
          "value": "xywh=pixel:1450.8155517578125,1539.5784912109375,160.96728515625,198.113525390625"
        }
      }
    ],
    "id": "https://crossreads.web.ox.ac.uk/annotations/d00df5d9-cf84-4b79-87fd-2461eecb0f2c",
    "generator": "https://github.com/kingsdigitallab/crossreads#2023-09-01-00",
    "creator": "https://api.github.com/users/simonastoyanova",
    "created": "2024-02-22T14:40:58.957Z",
    "modifiedBy": "https://api.github.com/users/simonastoyanova",
    "modified": "2024-02-22T14:41:19.520Z"
  }
]