[
  {
    "@context": "http://www.w3.org/ns/anno.jsonld",
    "type": "Annotation",
    "body": [
      {
        "type": "TextualBody",
        "purpose": "describing",
        "format": "application/json",
        "value": {
          "script": "latin",
          "components": null,
          "tags": null,
          "character": "punctuation"
        }
      }
    ],
    "target": [
      {
        "source": "https://apheleia.classics.ox.ac.uk/iipsrv/iipsrv.fcgi?IIIF=/inscription_images/ISic000198/ISic000198_tiled.tif",
        "selector": {
          "type": "FragmentSelector",
          "conformsTo": "http://www.w3.org/TR/media-frags/",
          "value": "xywh=pixel:1373.701416015625,3452.26953125,208.0191650390625,305.837890625"
        }
      },
      {
        "source": "http://sicily.classics.ox.ac.uk/inscription/ISic000198.xml",
        "selector": {
          "type": "XPathSelector",
          "value": "//*[@xml:id='ATεCo']",
          "refinedBy": {
            "type": "TextPositionSelector",
            "start": 0,
            "end": 1
          }
        }
      }
    ],
    "id": "https://sicily.classics.ox.ac.uk/annotations/054df3bf-f06a-44bc-9ea9-784e97770de2",
    "generator": "https://github.com/kingsdigitallab/crossreads#2023-09-01-00",
    "creator": "https://api.github.com/users/simonastoyanova",
    "created": "2025-06-04T12:57:05.927Z",
    "modifiedBy": "https://api.github.com/users/simonastoyanova",
    "modified": "2025-06-04T12:57:10.054Z"
  },
  {
    "@context": "http://www.w3.org/ns/anno.jsonld",
    "type": "Annotation",
    "body": [
      {
        "type": "TextualBody",
        "purpose": "describing",
        "format": "application/json",
        "value": {
          "script": "latin",
          "components": {
            "spine": {
              "features": [
                "on-baseline",
                "short"
              ]
            },
            "finial": {
              "features": [
                "serif"
              ]
            },
            "upper-hook": {
              "features": [
                "wide"
              ]
            },
            "lower-hook": {
              "features": [
                "wide"
              ]
            }
          },
          "tags": [
            "serif.wedged"
          ],
          "character": "S"
        }
      }
    ],
    "target": [
      {
        "source": "https://apheleia.classics.ox.ac.uk/iipsrv/iipsrv.fcgi?IIIF=/inscription_images/ISic000198/ISic000198_tiled.tif",
        "selector": {
          "type": "FragmentSelector",
          "conformsTo": "http://www.w3.org/TR/media-frags/",
          "value": "xywh=pixel:2133.962158203125,2784.874755859375,331.840087890625,494.045654296875"
        }
      },
      {
        "source": "http://sicily.classics.ox.ac.uk/inscription/ISic000198.xml",
        "selector": {
          "type": "XPathSelector",
          "value": "//*[@xml:id='ATεBο']",
          "refinedBy": {
            "type": "TextPositionSelector",
            "start": 3,
            "end": 4
          }
        }
      }
    ],
    "id": "https://sicily.classics.ox.ac.uk/annotations/094aa106-1ae1-4033-9053-3c6da646ec67",
    "generator": "https://github.com/kingsdigitallab/crossreads#2023-09-01-00",
    "creator": "https://api.github.com/users/simonastoyanova",
    "created": "2025-06-04T12:55:32.034Z",
    "modifiedBy": "https://api.github.com/users/simonastoyanova",
    "modified": "2025-07-04T14:50:45.342Z"
  },
  {
    "@context": "http://www.w3.org/ns/anno.jsonld",
    "type": "Annotation",
    "body": [
      {
        "type": "TextualBody",
        "purpose": "describing",
        "format": "application/json",
        "value": {
          "script": "latin",
          "components": {
            "apex": {
              "features": [
                "rounded",
                "sans-serif"
              ]
            },
            "left-stroke": {
              "features": [
                "diagonal",
                "on-baseline",
                "serif",
                "straight",
                "thin"
              ]
            },
            "left-bar": {
              "features": [
                "diagonal",
                "extending",
                "on-baseline",
                "serif",
                "thick",
                "curved"
              ]
            },
            "right-bar": {
              "features": [
                "diagonal",
                "on-baseline",
                "serif",
                "straight",
                "thin"
              ]
            },
            "right-stroke": {
              "features": [
                "diagonal",
                "extending",
                "on-baseline",
                "serif",
                "thick",
                "curved"
              ]
            }
          },
          "tags": [
            "serif.cursive",
            "type1",
            "type1.2",
            "type1.2.1"
          ],
          "character": "M"
        }
      }
    ],
    "target": [
      {
        "source": "https://apheleia.classics.ox.ac.uk/iipsrv/iipsrv.fcgi?IIIF=/inscription_images/ISic000198/ISic000198_tiled.tif",
        "selector": {
          "type": "FragmentSelector",
          "conformsTo": "http://www.w3.org/TR/media-frags/",
          "value": "xywh=pixel:825.131591796875,1955.9918212890625,847.2918701171875,519.9290771484375"
        }
      },
      {
        "source": "http://sicily.classics.ox.ac.uk/inscription/ISic000198.xml",
        "selector": {
          "type": "XPathSelector",
          "value": "//*[@xml:id='ATεBy']",
          "refinedBy": {
            "type": "TextPositionSelector",
            "start": 0,
            "end": 1
          }
        }
      }
    ],
    "id": "https://sicily.classics.ox.ac.uk/annotations/1f81af69-4ae0-41d0-a623-e79ad4778803",
    "generator": "https://github.com/kingsdigitallab/crossreads#2023-09-01-00",
    "creator": "https://api.github.com/users/simonastoyanova",
    "created": "2025-06-04T12:46:38.414Z",
    "modifiedBy": "https://api.github.com/users/simonastoyanova",
    "modified": "2026-01-29T14:30:38.284Z"
  },
  {
    "@context": "http://www.w3.org/ns/anno.jsonld",
    "type": "Annotation",
    "body": [
      {
        "type": "TextualBody",
        "purpose": "describing",
        "format": "application/json",
        "value": {
          "script": "latin",
          "components": {
            "downstroke": {
              "features": [
                "on-baseline",
                "serif",
                "straight",
                "vertical"
              ]
            },
            "top-bar": {
              "features": [
                "curved",
                "horizontal",
                "sans-serif",
                "touching"
              ]
            }
          },
          "tags": [
            "serif.curved"
          ],
          "character": "T"
        }
      }
    ],
    "target": [
      {
        "source": "https://apheleia.classics.ox.ac.uk/iipsrv/iipsrv.fcgi?IIIF=/inscription_images/ISic000198/ISic000198_tiled.tif",
        "selector": {
          "type": "FragmentSelector",
          "conformsTo": "http://www.w3.org/TR/media-frags/",
          "value": "xywh=pixel:2428.656005859375,2788.589111328125,355.365966796875,496.522216796875"
        }
      },
      {
        "source": "http://sicily.classics.ox.ac.uk/inscription/ISic000198.xml",
        "selector": {
          "type": "XPathSelector",
          "value": "//*[@xml:id='ATεBο']",
          "refinedBy": {
            "type": "TextPositionSelector",
            "start": 4,
            "end": 5
          }
        }
      }
    ],
    "id": "https://sicily.classics.ox.ac.uk/annotations/523ee7a9-95c2-4e43-a63e-573f36b63794",
    "generator": "https://github.com/kingsdigitallab/crossreads#2023-09-01-00",
    "creator": "https://api.github.com/users/simonastoyanova",
    "created": "2025-06-04T12:55:56.348Z",
    "modifiedBy": "https://api.github.com/users/simonastoyanova",
    "modified": "2025-06-04T12:56:13.118Z"
  },
  {
    "@context": "http://www.w3.org/ns/anno.jsonld",
    "type": "Annotation",
    "body": [
      {
        "type": "TextualBody",
        "purpose": "describing",
        "format": "application/json",
        "value": {
          "script": "latin",
          "components": {
            "downstroke": {
              "features": [
                "on-baseline",
                "serif",
                "straight",
                "vertical"
              ]
            }
          },
          "tags": [
            "serif.curved",
            "type1"
          ],
          "character": "I"
        }
      }
    ],
    "target": [
      {
        "source": "https://apheleia.classics.ox.ac.uk/iipsrv/iipsrv.fcgi?IIIF=/inscription_images/ISic000198/ISic000198_tiled.tif",
        "selector": {
          "type": "FragmentSelector",
          "conformsTo": "http://www.w3.org/TR/media-frags/",
          "value": "xywh=pixel:2739.446533203125,2820.782470703125,308.314208984375,481.66357421875"
        }
      },
      {
        "source": "http://sicily.classics.ox.ac.uk/inscription/ISic000198.xml",
        "selector": {
          "type": "XPathSelector",
          "value": "//*[@xml:id='ATεBο']",
          "refinedBy": {
            "type": "TextPositionSelector",
            "start": 5,
            "end": 6
          }
        }
      }
    ],
    "id": "https://sicily.classics.ox.ac.uk/annotations/7b4e8885-6e34-4fde-b7b7-d93c928c8bab",
    "generator": "https://github.com/kingsdigitallab/crossreads#2023-09-01-00",
    "creator": "https://api.github.com/users/simonastoyanova",
    "created": "2025-06-04T12:56:18.200Z",
    "modifiedBy": "https://api.github.com/users/simonastoyanova",
    "modified": "2025-09-29T16:00:40.122Z"
  },
  {
    "@context": "http://www.w3.org/ns/anno.jsonld",
    "type": "Annotation",
    "body": [
      {
        "type": "TextualBody",
        "purpose": "describing",
        "format": "application/json",
        "value": {
          "script": "latin",
          "components": {
            "left-stroke": {
              "features": [
                "diagonal",
                "on-baseline",
                "serif",
                "traversing",
                "straight",
                "thick"
              ]
            },
            "right-stroke": {
              "features": [
                "curved",
                "diagonal",
                "on-baseline",
                "sans-serif",
                "traversing",
                "thin"
              ]
            }
          },
          "tags": [
            "serif.cursive",
            "serif.wedged"
          ],
          "character": "X"
        }
      }
    ],
    "target": [
      {
        "source": "https://apheleia.classics.ox.ac.uk/iipsrv/iipsrv.fcgi?IIIF=/inscription_images/ISic000198/ISic000198_tiled.tif",
        "selector": {
          "type": "FragmentSelector",
          "conformsTo": "http://www.w3.org/TR/media-frags/",
          "value": "xywh=pixel:2337.028564453125,4070.135986328125,495.28369140625,539.859619140625"
        }
      },
      {
        "source": "http://sicily.classics.ox.ac.uk/inscription/ISic000198.xml",
        "selector": {
          "type": "XPathSelector",
          "value": "//*[@xml:id='ATεDΤ']",
          "refinedBy": {
            "type": "TextPositionSelector",
            "start": 1,
            "end": 2
          }
        }
      }
    ],
    "id": "https://sicily.classics.ox.ac.uk/annotations/7e54551c-47d6-48e5-ba42-0280f120e6f2",
    "generator": "https://github.com/kingsdigitallab/crossreads#2023-09-01-00",
    "creator": "https://api.github.com/users/simonastoyanova",
    "created": "2025-06-04T12:58:45.388Z",
    "modifiedBy": "https://api.github.com/users/simonastoyanova",
    "modified": "2025-07-04T17:06:58.665Z"
  },
  {
    "@context": "http://www.w3.org/ns/anno.jsonld",
    "type": "Annotation",
    "body": [
      {
        "type": "TextualBody",
        "purpose": "describing",
        "format": "application/json",
        "value": {
          "script": "latin",
          "components": {
            "right-stroke": {
              "features": [
                "diagonal",
                "extending",
                "on-baseline",
                "serif",
                "straight",
                "thick"
              ]
            },
            "left-stroke": {
              "features": [
                "diagonal",
                "on-baseline",
                "serif",
                "straight",
                "thin"
              ]
            },
            "crossbar": {
              "features": [
                "horizontal",
                "sans-serif",
                "short",
                "straight",
                "touching"
              ]
            },
            "apex": {
              "features": [
                "angular",
                "serif"
              ]
            }
          },
          "tags": [
            "serif.cursive",
            "serif.wedged",
            "type1.3.1",
            "type1.3.2"
          ],
          "character": "A"
        }
      }
    ],
    "target": [
      {
        "source": "https://apheleia.classics.ox.ac.uk/iipsrv/iipsrv.fcgi?IIIF=/inscription_images/ISic000198/ISic000198_tiled.tif",
        "selector": {
          "type": "FragmentSelector",
          "conformsTo": "http://www.w3.org/TR/media-frags/",
          "value": "xywh=pixel:1291.979736328125,2765.063232421875,541.0975341796875,526.2392578125"
        }
      },
      {
        "source": "http://sicily.classics.ox.ac.uk/inscription/ISic000198.xml",
        "selector": {
          "type": "XPathSelector",
          "value": "//*[@xml:id='ATεBο']",
          "refinedBy": {
            "type": "TextPositionSelector",
            "start": 1,
            "end": 2
          }
        }
      }
    ],
    "id": "https://sicily.classics.ox.ac.uk/annotations/889fca15-7d59-44a8-9f5d-c5d50c93a4f1",
    "generator": "https://github.com/kingsdigitallab/crossreads#2023-09-01-00",
    "creator": "https://api.github.com/users/simonastoyanova",
    "created": "2025-06-04T12:53:58.115Z",
    "modifiedBy": "https://api.github.com/users/simonastoyanova",
    "modified": "2025-09-22T15:08:15.781Z"
  },
  {
    "@context": "http://www.w3.org/ns/anno.jsonld",
    "type": "Annotation",
    "body": [
      {
        "type": "TextualBody",
        "purpose": "describing",
        "format": "application/json",
        "value": {
          "script": "latin",
          "components": {
            "right-stroke": {
              "features": [
                "diagonal",
                "extending",
                "serif",
                "straight",
                "long",
                "thick"
              ]
            },
            "left-stroke": {
              "features": [
                "diagonal",
                "on-baseline",
                "serif",
                "straight",
                "thin"
              ]
            },
            "crossbar": {
              "features": [
                "horizontal",
                "sans-serif",
                "short",
                "straight",
                "touching"
              ]
            },
            "apex": {
              "features": [
                "angular",
                "serif"
              ]
            }
          },
          "tags": [
            "serif.cursive",
            "serif.wedged",
            "type1.3.1",
            "type1.3.2"
          ],
          "character": "A"
        }
      }
    ],
    "target": [
      {
        "source": "https://apheleia.classics.ox.ac.uk/iipsrv/iipsrv.fcgi?IIIF=/inscription_images/ISic000198/ISic000198_tiled.tif",
        "selector": {
          "type": "FragmentSelector",
          "conformsTo": "http://www.w3.org/TR/media-frags/",
          "value": "xywh=pixel:2736.97021484375,3571.1376953125,487.8544921875,511.38037109375"
        }
      },
      {
        "source": "http://sicily.classics.ox.ac.uk/inscription/ISic000198.xml",
        "selector": {
          "type": "XPathSelector",
          "value": "//*[@xml:id='ATεDU']",
          "refinedBy": {
            "type": "TextPositionSelector",
            "start": 0,
            "end": 1
          }
        }
      }
    ],
    "id": "https://sicily.classics.ox.ac.uk/annotations/92c40a11-52ae-4cd7-be95-97e38ec06cf1",
    "generator": "https://github.com/kingsdigitallab/crossreads#2023-09-01-00",
    "creator": "https://api.github.com/users/simonastoyanova",
    "created": "2025-06-04T12:57:55.310Z",
    "modifiedBy": "https://api.github.com/users/simonastoyanova",
    "modified": "2025-09-22T15:08:15.781Z"
  },
  {
    "@context": "http://www.w3.org/ns/anno.jsonld",
    "type": "Annotation",
    "body": [
      {
        "type": "TextualBody",
        "purpose": "describing",
        "format": "application/json",
        "value": {
          "script": "latin",
          "components": {
            "downstroke": {
              "features": [
                "on-baseline",
                "serif",
                "straight",
                "vertical"
              ]
            },
            "bowl": {
              "features": [
                "closed",
                "round"
              ]
            }
          },
          "tags": [
            "serif.curved"
          ],
          "character": "D"
        }
      }
    ],
    "target": [
      {
        "source": "https://apheleia.classics.ox.ac.uk/iipsrv/iipsrv.fcgi?IIIF=/inscription_images/ISic000198/ISic000198_tiled.tif",
        "selector": {
          "type": "FragmentSelector",
          "conformsTo": "http://www.w3.org/TR/media-frags/",
          "value": "xywh=pixel:1332.2230224609375,1228.5191650390625,511.37060546875,524.2083740234375"
        }
      },
      {
        "source": "http://sicily.classics.ox.ac.uk/inscription/ISic000198.xml",
        "selector": {
          "type": "XPathSelector",
          "value": "//*[@xml:id='ATεAy']",
          "refinedBy": {
            "type": "TextPositionSelector",
            "start": 0,
            "end": 1
          }
        }
      }
    ],
    "id": "https://sicily.classics.ox.ac.uk/annotations/943e48a1-841a-4627-91c5-d4c03d158642",
    "generator": "https://github.com/kingsdigitallab/crossreads#2023-09-01-00",
    "creator": "https://api.github.com/users/simonastoyanova",
    "created": "2025-06-04T12:45:29.264Z",
    "modifiedBy": "https://api.github.com/users/simonastoyanova",
    "modified": "2025-06-04T12:46:06.767Z"
  },
  {
    "@context": "http://www.w3.org/ns/anno.jsonld",
    "type": "Annotation",
    "body": [
      {
        "type": "TextualBody",
        "purpose": "describing",
        "format": "application/json",
        "value": {
          "script": "latin",
          "components": {
            "apex": {
              "features": [
                "angular",
                "sans-serif"
              ]
            },
            "left-stroke": {
              "features": [
                "diagonal",
                "on-baseline",
                "serif",
                "straight",
                "thick"
              ]
            },
            "right-stroke": {
              "features": [
                "diagonal",
                "on-baseline",
                "serif",
                "straight",
                "thin"
              ]
            }
          },
          "tags": [
            "serif.wedged"
          ],
          "character": "U"
        }
      }
    ],
    "target": [
      {
        "source": "https://apheleia.classics.ox.ac.uk/iipsrv/iipsrv.fcgi?IIIF=/inscription_images/ISic000198/ISic000198_tiled.tif",
        "selector": {
          "type": "FragmentSelector",
          "conformsTo": "http://www.w3.org/TR/media-frags/",
          "value": "xywh=pixel:1966.51611328125,1979.858642578125,581.95849609375,551.003173828125"
        }
      },
      {
        "source": "http://sicily.classics.ox.ac.uk/inscription/ISic000198.xml",
        "selector": {
          "type": "XPathSelector",
          "value": "//*[@xml:id='ATεBy']",
          "refinedBy": {
            "type": "TextPositionSelector",
            "start": 2,
            "end": 3
          }
        }
      }
    ],
    "id": "https://sicily.classics.ox.ac.uk/annotations/9464ae0b-e6c7-4ecd-8b45-d8adc33350b8",
    "generator": "https://github.com/kingsdigitallab/crossreads#2023-09-01-00",
    "creator": "https://api.github.com/users/simonastoyanova",
    "created": "2025-06-04T12:48:41.836Z",
    "modifiedBy": "https://api.github.com/users/simonastoyanova",
    "modified": "2025-07-04T17:06:10.325Z"
  },
  {
    "@context": "http://www.w3.org/ns/anno.jsonld",
    "type": "Annotation",
    "body": [
      {
        "type": "TextualBody",
        "purpose": "describing",
        "format": "application/json",
        "value": {
          "script": "latin",
          "components": {
            "downstroke": {
              "features": [
                "on-baseline",
                "serif",
                "straight",
                "vertical",
                "high"
              ]
            },
            "middle-bar": {
              "features": [
                "curved",
                "ascending",
                "diagonal",
                "one",
                "sans-serif",
                "short",
                "touching"
              ]
            },
            "top-bar": {
              "features": [
                "ascending",
                "curved",
                "diagonal",
                "long",
                "sans-serif",
                "touching"
              ]
            }
          },
          "tags": [
            "serif.curved",
            "type1.2",
            "type1",
            "type1.2.1"
          ],
          "character": "F"
        }
      }
    ],
    "target": [
      {
        "source": "https://apheleia.classics.ox.ac.uk/iipsrv/iipsrv.fcgi?IIIF=/inscription_images/ISic000198/ISic000198_tiled.tif",
        "selector": {
          "type": "FragmentSelector",
          "conformsTo": "http://www.w3.org/TR/media-frags/",
          "value": "xywh=pixel:993.5711669921875,2687.05615234375,502.7130126953125,604.246337890625"
        }
      },
      {
        "source": "http://sicily.classics.ox.ac.uk/inscription/ISic000198.xml",
        "selector": {
          "type": "XPathSelector",
          "value": "//*[@xml:id='ATεBο']",
          "refinedBy": {
            "type": "TextPositionSelector",
            "start": 0,
            "end": 1
          }
        }
      }
    ],
    "id": "https://sicily.classics.ox.ac.uk/annotations/a44a9716-3f6b-4b60-8bcb-b68dfa0e5cc5",
    "generator": "https://github.com/kingsdigitallab/crossreads#2023-09-01-00",
    "creator": "https://api.github.com/users/simonastoyanova",
    "created": "2025-06-04T12:50:05.017Z",
    "modifiedBy": "https://api.github.com/users/simonastoyanova",
    "modified": "2025-09-24T15:18:53.407Z"
  },
  {
    "@context": "http://www.w3.org/ns/anno.jsonld",
    "type": "Annotation",
    "body": [
      {
        "type": "TextualBody",
        "purpose": "describing",
        "format": "application/json",
        "value": {
          "script": "latin",
          "components": {
            "downstroke": {
              "features": [
                "on-baseline",
                "serif",
                "straight",
                "vertical"
              ]
            }
          },
          "tags": [
            "serif.curved",
            "serif.wedged",
            "type1"
          ],
          "character": "I"
        }
      }
    ],
    "target": [
      {
        "source": "https://apheleia.classics.ox.ac.uk/iipsrv/iipsrv.fcgi?IIIF=/inscription_images/ISic000198/ISic000198_tiled.tif",
        "selector": {
          "type": "FragmentSelector",
          "conformsTo": "http://www.w3.org/TR/media-frags/",
          "value": "xywh=pixel:2569.524169921875,1984.8116455078125,347.93701171875,539.8592529296875"
        }
      },
      {
        "source": "http://sicily.classics.ox.ac.uk/inscription/ISic000198.xml",
        "selector": {
          "type": "XPathSelector",
          "value": "//*[@xml:id='ATεBy']",
          "refinedBy": {
            "type": "TextPositionSelector",
            "start": 3,
            "end": 4
          }
        }
      }
    ],
    "id": "https://sicily.classics.ox.ac.uk/annotations/af2cce6f-8652-4ece-b82b-a42c65847c60",
    "generator": "https://github.com/kingsdigitallab/crossreads#2023-09-01-00",
    "creator": "https://api.github.com/users/simonastoyanova",
    "created": "2025-06-04T12:49:23.587Z",
    "modifiedBy": "https://api.github.com/users/simonastoyanova",
    "modified": "2025-09-29T16:00:40.122Z"
  },
  {
    "@context": "http://www.w3.org/ns/anno.jsonld",
    "type": "Annotation",
    "body": [
      {
        "type": "TextualBody",
        "purpose": "describing",
        "format": "application/json",
        "value": {
          "script": "latin",
          "components": null,
          "tags": null,
          "character": "punctuation"
        }
      }
    ],
    "target": [
      {
        "source": "https://apheleia.classics.ox.ac.uk/iipsrv/iipsrv.fcgi?IIIF=/inscription_images/ISic000198/ISic000198_tiled.tif",
        "selector": {
          "type": "FragmentSelector",
          "conformsTo": "http://www.w3.org/TR/media-frags/",
          "value": "xywh=pixel:2401.415283203125,3543.89697265625,236.498046875,376.415771484375"
        }
      },
      {
        "source": "http://sicily.classics.ox.ac.uk/inscription/ISic000198.xml",
        "selector": {
          "type": "XPathSelector",
          "value": "//*[@xml:id='ATεCο']",
          "refinedBy": {
            "type": "TextPositionSelector",
            "start": 0,
            "end": 1
          }
        }
      }
    ],
    "id": "https://sicily.classics.ox.ac.uk/annotations/b7d7327b-0c22-4343-bff6-4e58456a10a1",
    "generator": "https://github.com/kingsdigitallab/crossreads#2023-09-01-00",
    "creator": "https://api.github.com/users/simonastoyanova",
    "created": "2025-06-04T12:56:49.576Z",
    "modifiedBy": "https://api.github.com/users/simonastoyanova",
    "modified": "2025-06-04T12:56:57.893Z"
  },
  {
    "@context": "http://www.w3.org/ns/anno.jsonld",
    "type": "Annotation",
    "body": [
      {
        "type": "TextualBody",
        "purpose": "describing",
        "format": "application/json",
        "value": {
          "script": "latin",
          "components": {
            "apex": {
              "features": [
                "rounded",
                "sans-serif"
              ]
            },
            "left-stroke": {
              "features": [
                "diagonal",
                "on-baseline",
                "serif",
                "straight",
                "thick"
              ]
            },
            "right-stroke": {
              "features": [
                "diagonal",
                "on-baseline",
                "serif",
                "straight",
                "thin"
              ]
            }
          },
          "tags": [
            "serif.wedged"
          ],
          "character": "U"
        }
      }
    ],
    "target": [
      {
        "source": "https://apheleia.classics.ox.ac.uk/iipsrv/iipsrv.fcgi?IIIF=/inscription_images/ISic000198/ISic000198_tiled.tif",
        "selector": {
          "type": "FragmentSelector",
          "conformsTo": "http://www.w3.org/TR/media-frags/",
          "value": "xywh=pixel:1626.2962646484375,2778.68359375,584.4349365234375,502.713134765625"
        }
      },
      {
        "source": "http://sicily.classics.ox.ac.uk/inscription/ISic000198.xml",
        "selector": {
          "type": "XPathSelector",
          "value": "//*[@xml:id='ATεBο']",
          "refinedBy": {
            "type": "TextPositionSelector",
            "start": 2,
            "end": 3
          }
        }
      }
    ],
    "id": "https://sicily.classics.ox.ac.uk/annotations/c1dd35b3-0c18-4b7b-bc07-9ee455080215",
    "generator": "https://github.com/kingsdigitallab/crossreads#2023-09-01-00",
    "creator": "https://api.github.com/users/simonastoyanova",
    "created": "2025-06-04T12:55:00.866Z",
    "modifiedBy": "https://api.github.com/users/simonastoyanova",
    "modified": "2025-07-04T17:06:36.040Z"
  },
  {
    "@context": "http://www.w3.org/ns/anno.jsonld",
    "type": "Annotation",
    "body": [
      {
        "type": "TextualBody",
        "purpose": "describing",
        "format": "application/json",
        "value": {
          "script": "latin",
          "components": null,
          "tags": null,
          "character": "punctuation"
        }
      }
    ],
    "target": [
      {
        "source": "https://apheleia.classics.ox.ac.uk/iipsrv/iipsrv.fcgi?IIIF=/inscription_images/ISic000198/ISic000198_tiled.tif",
        "selector": {
          "type": "FragmentSelector",
          "conformsTo": "http://www.w3.org/TR/media-frags/",
          "value": "xywh=pixel:2031.880615234375,1239.2171630859375,513.51025390625,716.7747802734375"
        }
      },
      {
        "source": "http://sicily.classics.ox.ac.uk/inscription/ISic000198.xml",
        "selector": {
          "type": "XPathSelector",
          "value": "//*[@xml:id='ATεAΤ']",
          "refinedBy": {
            "type": "TextPositionSelector",
            "start": 0,
            "end": 1
          }
        }
      }
    ],
    "id": "https://sicily.classics.ox.ac.uk/annotations/d2fbca5e-b050-4b66-8f42-2ad17e394d8a",
    "generator": "https://github.com/kingsdigitallab/crossreads#2023-09-01-00",
    "creator": "https://api.github.com/users/simonastoyanova",
    "created": "2025-06-04T12:46:18.199Z",
    "modifiedBy": "https://api.github.com/users/simonastoyanova",
    "modified": "2025-06-04T12:46:22.541Z"
  },
  {
    "@context": "http://www.w3.org/ns/anno.jsonld",
    "type": "Annotation",
    "body": [
      {
        "type": "TextualBody",
        "purpose": "describing",
        "format": "application/json",
        "value": {
          "script": "latin",
          "components": {
            "top-bar": {
              "features": [
                "ascending",
                "diagonal",
                "curved",
                "parallel",
                "sans-serif",
                "touching"
              ]
            },
            "bottom-bar": {
              "features": [
                "curved",
                "horizontal",
                "on-baseline",
                "sans-serif",
                "touching"
              ]
            },
            "downstroke": {
              "features": [
                "on-baseline",
                "serif",
                "straight",
                "vertical"
              ]
            },
            "middle-bar": {
              "features": [
                "ascending",
                "curved",
                "diagonal",
                "equal-length",
                "one",
                "sans-serif",
                "touching"
              ]
            }
          },
          "tags": [
            "serif.curved",
            "type2",
            "type2.2"
          ],
          "character": "E"
        }
      }
    ],
    "target": [
      {
        "source": "https://apheleia.classics.ox.ac.uk/iipsrv/iipsrv.fcgi?IIIF=/inscription_images/ISic000198/ISic000198_tiled.tif",
        "selector": {
          "type": "FragmentSelector",
          "conformsTo": "http://www.w3.org/TR/media-frags/",
          "value": "xywh=pixel:1710.936767578125,1932.4559326171875,320.9439697265625,537.0462646484375"
        }
      },
      {
        "source": "http://sicily.classics.ox.ac.uk/inscription/ISic000198.xml",
        "selector": {
          "type": "XPathSelector",
          "value": "//*[@xml:id='ATεBy']",
          "refinedBy": {
            "type": "TextPositionSelector",
            "start": 1,
            "end": 2
          }
        }
      }
    ],
    "id": "https://sicily.classics.ox.ac.uk/annotations/e4dd2e1c-49fd-4303-84c8-5731bc5b3fac",
    "generator": "https://github.com/kingsdigitallab/crossreads#2023-09-01-00",
    "creator": "https://api.github.com/users/simonastoyanova",
    "created": "2025-06-04T12:47:30.629Z",
    "modifiedBy": "https://api.github.com/users/simonastoyanova",
    "modified": "2025-09-24T14:24:57.207Z"
  },
  {
    "@context": "http://www.w3.org/ns/anno.jsonld",
    "type": "Annotation",
    "body": [
      {
        "type": "TextualBody",
        "purpose": "describing",
        "format": "application/json",
        "value": {
          "script": "latin",
          "components": {
            "apex": {
              "features": [
                "rounded",
                "sans-serif"
              ]
            },
            "left-stroke": {
              "features": [
                "diagonal",
                "on-baseline",
                "serif",
                "straight"
              ]
            },
            "right-stroke": {
              "features": [
                "diagonal",
                "on-baseline",
                "serif",
                "straight"
              ]
            }
          },
          "tags": [
            "serif.cursive"
          ],
          "character": "U"
        }
      }
    ],
    "target": [
      {
        "source": "https://apheleia.classics.ox.ac.uk/iipsrv/iipsrv.fcgi?IIIF=/inscription_images/ISic000198/ISic000198_tiled.tif",
        "selector": {
          "type": "FragmentSelector",
          "conformsTo": "http://www.w3.org/TR/media-frags/",
          "value": "xywh=pixel:1679.5391845703125,3527.80029296875,569.5762939453125,459.375732421875"
        }
      },
      {
        "source": "http://sicily.classics.ox.ac.uk/inscription/ISic000198.xml",
        "selector": {
          "type": "XPathSelector",
          "value": "//*[@xml:id='ATεCΤ']",
          "refinedBy": {
            "type": "TextPositionSelector",
            "start": 0,
            "end": 1
          }
        }
      }
    ],
    "id": "https://sicily.classics.ox.ac.uk/annotations/eb59785d-2405-4dbe-8370-ec2d8c266293",
    "generator": "https://github.com/kingsdigitallab/crossreads#2023-09-01-00",
    "creator": "https://api.github.com/users/simonastoyanova",
    "created": "2025-06-04T12:57:16.709Z",
    "modifiedBy": "https://api.github.com/users/simonastoyanova",
    "modified": "2025-06-04T12:57:45.279Z"
  }
]