{
  "meta": {
    "@context": "http://schema.org",
    "dc:modified": "2024-10-11T13:12:50.522Z",
    "dc:creator": "https://github.com/kingsdigitallab/crossreads/blob/main/tools/index.mjs",
    "dc:source": "https://github.com/kingsdigitallab/crossreads/tree/main/annotations"
  },
  "data": {
    "SC": {
      "latin-1|I": 175,
      "latin-1|N": 80,
      "latin-1|A": 142,
      "latin-1|L": 73,
      "latin-1|O": 87,
      "latin-1|C": 55,
      "latin-1|R": 65,
      "latin-1|U": 92,
      "latin-1|E": 103,
      "latin-1|S": 63,
      "latin-1|T": 65,
      "latin-1|punctuation": 95,
      "latin-1|G": 15,
      "latin-1|M": 65,
      "latin-1|P": 57,
      "latin-1|D": 29,
      "latin-1|B": 26,
      "latin-1|F": 33,
      "latin-1|H": 9,
      "latin-1|Q": 15,
      "latin-1|X": 20,
      "latin-1|ligature": 3,
      "latin-1|Y": 1,
      "greek-1|Ω": 84,
      "greek-1|Γ": 24,
      "greek-1|Ι": 180,
      "greek-1|Υ": 91,
      "greek-1|Σ": 172,
      "greek-1|Ο": 181,
      "greek-1|Η": 20,
      "greek-1|Ν": 124,
      "greek-1|Φ": 33,
      "greek-1|Κ": 86,
      "greek-1|Λ": 54,
      "greek-1|Α": 254,
      "greek-1|Ρ": 113,
      "greek-1|Θ": 41,
      "greek-1|Ε": 193,
      "greek-1|Ξ": 8,
      "greek-1|Τ": 112,
      "greek-1|Μ": 95,
      "greek-1|Π": 74,
      "greek-1|Ψ": 3,
      "greek-1|Δ": 41,
      "greek-1|Χ": 16,
      "greek-1|Β": 16,
      "greek-1|Ζ": 7,
      "greek-1|ϙ": 6,
      "greek-1|ϝ": 4
    },
    "Sc": {
      "latin-1|downstroke": 624,
      "latin-1|left-stroke": 406,
      "latin-1|middle-bar": 207,
      "latin-1|right-stroke": 403,
      "latin-1|crossbar": 143,
      "latin-1|apex": 292,
      "latin-1|bottom-bar": 172,
      "latin-1|body": 172,
      "latin-1|bowl": 150,
      "latin-1|right-bar": 128,
      "latin-1|top-bar": 190,
      "latin-1|spine": 63,
      "latin-1|tail": 26,
      "latin-1|left-bar": 64,
      "latin-1|foot": 88,
      "latin-1|lower-bowl": 26,
      "latin-1|upper-bowl": 26,
      "latin-1|finial": 74,
      "latin-1|hook": 56,
      "greek-1|body": 291,
      "greek-1|feet": 70,
      "greek-1|top-bar": 447,
      "greek-1|downstroke": 653,
      "greek-1|apex": 453,
      "greek-1|left-stroke": 602,
      "greek-1|right-stroke": 602,
      "greek-1|bottom-bar": 304,
      "greek-1|middle-bar": 276,
      "greek-1|crossbar": 280,
      "greek-1|middle-stroke": 105,
      "greek-1|upper-bar": 70,
      "greek-1|lower-bar": 70,
      "greek-1|bowl": 105,
      "greek-1|left-bar": 87,
      "greek-1|right-bar": 109,
      "greek-1|lower-bowl": 11,
      "greek-1|upper-bowl": 11,
      "greek-1|tail": 2
    },
    "SCc": {
      "latin-1|I|downstroke": 175,
      "latin-1|N|left-stroke": 79,
      "latin-1|N|middle-bar": 77,
      "latin-1|N|right-stroke": 78,
      "latin-1|A|right-stroke": 141,
      "latin-1|A|left-stroke": 142,
      "latin-1|A|crossbar": 134,
      "latin-1|A|apex": 136,
      "latin-1|L|downstroke": 73,
      "latin-1|L|bottom-bar": 73,
      "latin-1|O|body": 87,
      "latin-1|C|body": 55,
      "latin-1|R|downstroke": 65,
      "latin-1|R|bowl": 64,
      "latin-1|R|right-bar": 64,
      "latin-1|U|apex": 92,
      "latin-1|U|left-stroke": 92,
      "latin-1|U|right-stroke": 92,
      "latin-1|E|top-bar": 96,
      "latin-1|E|bottom-bar": 99,
      "latin-1|E|downstroke": 102,
      "latin-1|E|middle-bar": 98,
      "latin-1|S|spine": 63,
      "latin-1|T|downstroke": 65,
      "latin-1|T|top-bar": 64,
      "latin-1|G|body": 15,
      "latin-1|G|tail": 11,
      "latin-1|M|apex": 64,
      "latin-1|M|left-stroke": 64,
      "latin-1|M|left-bar": 64,
      "latin-1|M|right-bar": 64,
      "latin-1|M|right-stroke": 64,
      "latin-1|P|downstroke": 57,
      "latin-1|P|bowl": 57,
      "latin-1|D|downstroke": 29,
      "latin-1|D|bowl": 29,
      "latin-1|P|foot": 12,
      "latin-1|B|lower-bowl": 26,
      "latin-1|B|upper-bowl": 26,
      "latin-1|B|downstroke": 26,
      "latin-1|S|finial": 34,
      "latin-1|S|hook": 34,
      "latin-1|F|downstroke": 32,
      "latin-1|F|middle-bar": 32,
      "latin-1|F|top-bar": 30,
      "latin-1|H|crossbar": 9,
      "latin-1|H|left-stroke": 9,
      "latin-1|H|right-stroke": 9,
      "latin-1|Q|body": 15,
      "latin-1|Q|tail": 15,
      "latin-1|I|foot": 51,
      "latin-1|R|finial": 11,
      "latin-1|T|foot": 16,
      "latin-1|C|hook": 22,
      "latin-1|C|finial": 21,
      "latin-1|F|foot": 9,
      "latin-1|E|finial": 5,
      "latin-1|G|finial": 3,
      "latin-1|X|left-stroke": 20,
      "latin-1|X|right-stroke": 19,
      "greek-1|Ω|body": 71,
      "greek-1|Ω|feet": 70,
      "greek-1|Γ|top-bar": 15,
      "greek-1|Γ|downstroke": 19,
      "greek-1|Ι|downstroke": 127,
      "greek-1|Υ|downstroke": 60,
      "greek-1|Υ|apex": 72,
      "greek-1|Υ|left-stroke": 79,
      "greek-1|Υ|right-stroke": 79,
      "greek-1|Σ|apex": 121,
      "greek-1|Σ|bottom-bar": 121,
      "greek-1|Σ|middle-bar": 120,
      "greek-1|Σ|top-bar": 117,
      "greek-1|Ο|body": 149,
      "greek-1|Η|left-stroke": 18,
      "greek-1|Η|crossbar": 17,
      "greek-1|Η|right-stroke": 17,
      "greek-1|Ν|right-stroke": 105,
      "greek-1|Ν|left-stroke": 106,
      "greek-1|Ν|middle-stroke": 105,
      "greek-1|Φ|body": 33,
      "greek-1|Φ|crossbar": 33,
      "greek-1|Κ|downstroke": 72,
      "greek-1|Κ|upper-bar": 70,
      "greek-1|Κ|lower-bar": 70,
      "greek-1|Λ|left-stroke": 43,
      "greek-1|Λ|right-stroke": 42,
      "greek-1|Α|apex": 199,
      "greek-1|Α|crossbar": 193,
      "greek-1|Α|left-stroke": 198,
      "greek-1|Α|right-stroke": 201,
      "greek-1|Λ|downstroke": 1,
      "greek-1|Ρ|downstroke": 91,
      "greek-1|Ρ|bowl": 91,
      "greek-1|Θ|body": 38,
      "greek-1|Θ|crossbar": 37,
      "greek-1|Ε|bottom-bar": 144,
      "greek-1|Ε|downstroke": 147,
      "greek-1|Ε|middle-bar": 145,
      "greek-1|Ε|top-bar": 143,
      "greek-1|Ξ|bottom-bar": 6,
      "greek-1|Ξ|middle-bar": 6,
      "greek-1|Ξ|top-bar": 6,
      "greek-1|Τ|downstroke": 92,
      "greek-1|Τ|top-bar": 92,
      "greek-1|Μ|right-stroke": 76,
      "greek-1|Μ|left-stroke": 75,
      "greek-1|Μ|left-bar": 73,
      "greek-1|Μ|right-bar": 75,
      "greek-1|Π|left-stroke": 61,
      "greek-1|Π|right-stroke": 60,
      "greek-1|Π|top-bar": 62,
      "greek-1|Μ|apex": 58,
      "greek-1|Ψ|downstroke": 3,
      "greek-1|Ψ|left-bar": 2,
      "greek-1|Ψ|right-bar": 2,
      "greek-1|Δ|left-stroke": 19,
      "greek-1|Δ|right-stroke": 19,
      "greek-1|Δ|bottom-bar": 19,
      "greek-1|Χ|left-bar": 12,
      "greek-1|Χ|right-bar": 12,
      "greek-1|Ξ|downstroke": 4,
      "greek-1|Ζ|top-bar": 6,
      "greek-1|Ζ|downstroke": 6,
      "greek-1|Ζ|bottom-bar": 6,
      "greek-1|Β|downstroke": 9,
      "greek-1|Β|lower-bowl": 10,
      "greek-1|Β|upper-bowl": 10,
      "greek-1|Β|left-stroke": 2,
      "greek-1|Β|middle-bar": 2,
      "greek-1|Β|right-stroke": 2,
      "greek-1|Ρ|right-bar": 20,
      "greek-1|Δ|bowl": 11,
      "greek-1|Δ|downstroke": 10,
      "greek-1|ϙ|bowl": 3,
      "greek-1|ϙ|downstroke": 3,
      "greek-1|Ι|apex": 3,
      "greek-1|Ι|bottom-bar": 3,
      "greek-1|Ι|middle-bar": 2,
      "greek-1|Ι|top-bar": 3,
      "greek-1|Ε|lower-bowl": 1,
      "greek-1|Ε|upper-bowl": 1,
      "greek-1|Χ|downstroke": 6,
      "greek-1|Η|bottom-bar": 2,
      "greek-1|Π|downstroke": 1,
      "greek-1|Γ|bottom-bar": 3,
      "greek-1|ϝ|downstroke": 2,
      "greek-1|ϝ|top-bar": 2,
      "greek-1|ϝ|middle-bar": 1,
      "greek-1|Η|top-bar": 1,
      "greek-1|Π|tail": 2,
      "greek-1|Ψ|right-stroke": 1,
      "greek-1|Ψ|left-stroke": 1
    },
    "cf": {
      "downstroke|on-baseline": 1125,
      "downstroke|serif": 732,
      "downstroke|straight": 1253,
      "downstroke|vertical": 1076,
      "left-stroke|on-baseline": 871,
      "left-stroke|serif": 477,
      "left-stroke|straight": 983,
      "left-stroke|vertical": 294,
      "middle-bar|diagonal": 169,
      "middle-bar|sans-serif": 371,
      "middle-bar|straight": 451,
      "middle-bar|touching": 461,
      "right-stroke|serif": 472,
      "right-stroke|straight": 959,
      "right-stroke|on-baseline": 780,
      "right-stroke|vertical": 285,
      "right-stroke|diagonal": 713,
      "right-stroke|long": 36,
      "left-stroke|long": 5,
      "left-stroke|diagonal": 714,
      "crossbar|touching": 362,
      "crossbar|sans-serif": 398,
      "crossbar|short": 41,
      "crossbar|straight": 401,
      "apex|square": 8,
      "bottom-bar|curved": 135,
      "bottom-bar|serif": 144,
      "bottom-bar|below-baseline": 69,
      "body|oval": 130,
      "body|circular": 302,
      "bowl|rounded": 110,
      "bowl|closed": 182,
      "right-bar|diagonal": 236,
      "right-bar|on-baseline": 150,
      "right-bar|serif": 38,
      "right-bar|straight": 177,
      "apex|angular": 713,
      "top-bar|straight": 541,
      "top-bar|serif": 185,
      "top-bar|short": 38,
      "top-bar|touching": 617,
      "top-bar|horizontal": 477,
      "bottom-bar|on-baseline": 340,
      "bottom-bar|short": 30,
      "bottom-bar|straight": 337,
      "bottom-bar|horizontal": 364,
      "bottom-bar|touching": 438,
      "middle-bar|serif": 108,
      "middle-bar|short": 116,
      "middle-bar|horizontal": 211,
      "spine|on-baseline": 62,
      "crossbar|horizontal": 260,
      "apex|serif": 47,
      "downstroke|curved": 21,
      "bowl|round": 133,
      "right-bar|curved": 57,
      "right-bar|sans-serif": 198,
      "tail|on-baseline": 9,
      "tail|straight": 6,
      "tail|short": 8,
      "tail|vertical": 9,
      "tail|serif": 5,
      "left-bar|diagonal": 151,
      "left-bar|on-baseline": 88,
      "left-bar|straight": 143,
      "left-bar|sans-serif": 143,
      "bowl|open": 70,
      "tail|curved": 19,
      "tail|sans-serif": 19,
      "foot|curved": 86,
      "right-stroke|curved": 44,
      "right-stroke|below-baseline": 16,
      "right-stroke|sans-serif": 527,
      "downstroke|sans-serif": 540,
      "lower-bowl|closed": 23,
      "lower-bowl|round": 25,
      "upper-bowl|closed": 23,
      "upper-bowl|round": 25,
      "left-stroke|sans-serif": 527,
      "top-bar|parallel": 228,
      "bottom-bar|parallel": 180,
      "middle-bar|parallel": 229,
      "middle-bar|descending": 68,
      "bottom-bar|sans-serif": 324,
      "top-bar|sans-serif": 446,
      "right-stroke|short": 51,
      "right-stroke|traversing": 23,
      "right-bar|below-baseline": 13,
      "left-bar|traversing": 15,
      "top-bar|ascending": 73,
      "top-bar|curved": 99,
      "middle-bar|ascending": 32,
      "middle-bar|curved": 29,
      "apex|sans-serif": 382,
      "downstroke|high": 18,
      "spine|long": 29,
      "finial|serif": 62,
      "hook|wide": 19,
      "lower-bowl|rounded": 9,
      "upper-bowl|rounded": 9,
      "right-bar|short": 28,
      "tail|below-baseline": 17,
      "tail|diagonal": 5,
      "foot|long": 81,
      "hook|narrow": 37,
      "finial|sans-serif": 12,
      "left-bar|serif": 6,
      "middle-bar|traversing": 3,
      "left-stroke|traversing": 17,
      "tail|long": 8,
      "top-bar|descending": 1,
      "right-bar|above-baseline": 68,
      "top-bar|long": 56,
      "left-stroke|short": 49,
      "left-bar|long": 5,
      "right-bar|long": 1,
      "bottom-bar|diagonal": 96,
      "crossbar|descending": 23,
      "lower-bowl|open": 12,
      "lower-bowl|angular": 3,
      "upper-bowl|open": 12,
      "upper-bowl|angular": 3,
      "middle-bar|not-touching": 4,
      "foot|straight": 1,
      "middle-bar|long": 4,
      "left-stroke|curved": 24,
      "downstroke|traversing": 14,
      "top-bar|traversing": 6,
      "left-bar|short": 9,
      "apex|rounded": 25,
      "bottom-bar|long": 20,
      "right-stroke|above-baseline": 125,
      "left-bar|curved": 7,
      "left-stroke|below-baseline": 32,
      "crossbar|curved": 4,
      "top-bar|diagonal": 106,
      "crossbar|ascending": 70,
      "downstroke|diagonal": 9,
      "downstroke|below-baseline": 112,
      "crossbar|not-touching": 31,
      "crossbar|broken": 12,
      "feet|sans-serif": 55,
      "feet|short": 26,
      "feet|straight": 68,
      "feet|touching": 63,
      "body|small": 88,
      "middle-stroke|descending": 94,
      "middle-stroke|diagonal": 90,
      "middle-stroke|above-baseline": 52,
      "middle-stroke|straight": 105,
      "middle-stroke|touching": 102,
      "crossbar|traversing": 29,
      "crossbar|vertical": 47,
      "upper-bar|converging": 58,
      "upper-bar|diagonal": 65,
      "upper-bar|sans-serif": 57,
      "upper-bar|short": 16,
      "upper-bar|straight": 62,
      "upper-bar|touching": 63,
      "lower-bar|above-baseline": 51,
      "lower-bar|converging": 57,
      "lower-bar|diagonal": 64,
      "lower-bar|sans-serif": 60,
      "lower-bar|straight": 64,
      "lower-bar|touching": 62,
      "middle-stroke|on-baseline": 50,
      "left-bar|above-baseline": 59,
      "upper-bar|curved": 5,
      "lower-bar|curved": 5,
      "lower-bar|on-baseline": 14,
      "body|rhomboid": 27,
      "left-stroke|above-baseline": 18,
      "upper-bar|serif": 13,
      "downstroke|above-baseline": 2,
      "upper-bar|not-touching": 4,
      "lower-bar|not-touching": 4,
      "lower-bar|below-baseline": 1,
      "right-bar|traversing": 11,
      "body|closed": 16,
      "feet|long": 30,
      "body|open": 19,
      "bottom-bar|above-baseline": 2,
      "lower-bar|serif": 10,
      "crossbar|point": 4,
      "crossbar|serif": 13,
      "crossbar|long": 21,
      "feet|serif": 15,
      "upper-bar|not-converging": 11,
      "lower-bar|not-converging": 11,
      "bowl|angular": 13,
      "feet|not-touching": 6,
      "feet|curved": 1,
      "middle-stroke|short": 3,
      "middle-stroke|not-touching": 4,
      "middle-stroke|ascending": 2,
      "top-bar|not-touching": 4,
      "bottom-bar|vertical": 1,
      "body|square": 5,
      "middle-stroke|below-baseline": 1
    },
    "c": {
      "downstroke": 1277,
      "left-stroke": 1008,
      "middle-bar": 483,
      "right-stroke": 1005,
      "crossbar": 423,
      "apex": 745,
      "bottom-bar": 476,
      "body": 463,
      "bowl": 255,
      "right-bar": 237,
      "top-bar": 637,
      "spine": 63,
      "tail": 28,
      "left-bar": 151,
      "foot": 88,
      "lower-bowl": 37,
      "upper-bowl": 37,
      "finial": 74,
      "hook": 56,
      "feet": 70,
      "middle-stroke": 105,
      "upper-bar": 70,
      "lower-bar": 70
    },
    "f": {
      "on-baseline": 3489,
      "serif": 2327,
      "straight": 5551,
      "vertical": 1712,
      "diagonal": 2418,
      "sans-serif": 4059,
      "touching": 2168,
      "long": 296,
      "short": 415,
      "square": 13,
      "curved": 536,
      "below-baseline": 261,
      "oval": 130,
      "circular": 302,
      "rounded": 153,
      "closed": 244,
      "angular": 732,
      "horizontal": 1312,
      "round": 183,
      "open": 113,
      "parallel": 637,
      "descending": 186,
      "traversing": 118,
      "ascending": 177,
      "high": 18,
      "wide": 19,
      "narrow": 37,
      "above-baseline": 377,
      "not-touching": 57,
      "broken": 12,
      "small": 88,
      "converging": 115,
      "rhomboid": 27,
      "point": 4,
      "not-converging": 22
    },
    "t": {
      "test": 3,
      "serif.hairline": 37,
      "test3": 2,
      "testtag": 1,
      "incomplete": 183,
      "serif.wedged": 76,
      "serif.slab": 369,
      "type1.3": 172,
      "tick": 1,
      "type1.1": 98,
      "serif.curved": 98,
      "leaf": 1,
      "type2": 28,
      "type2.1": 19,
      "tall": 3,
      "ae": 2,
      "supraline": 1,
      "type1.2": 25,
      "type3": 5,
      "serif.cursive": 6,
      "an": 1,
      "type1.4": 18,
      "short": 1,
      "terminal": 113,
      "two-mid-bar": 20,
      "one-mid-bar": 12,
      "m.exemplar": 1,
      "three-mid-bar": 2,
      "test0": 1,
      "overstrike": 1
    }
  }
}